{
  "imagePath": "images/official_correspondence/foundation_accident.png",
  "extractedText": "FEDERAL BUREAU OF CONTROL OREAU ¢\nS 2\n\nMr. Wilder, = 20\n| have some bad news. You remember S Ei\":fr:’, ’8\nthat Robert Ricardo fella we brought in as \" 5‘“ ‘K_[\"ill 3£: N\na “special consultant” to map the lower é,&% &Q}d’\ncaves? Well, today he found a chamber ‘osh = S\nwith weird eyes covering every inch of\nthe walls, and a strange black pillar in the center. Kinda looks like\nthe one at the Crossroads, but smaller.\nWe had a Bureau member shadowing him, but whatever happened\nin there did a number on our guest. The docs are taking a look but\nit's pretty clear Mr. Adventure'’s exploring days are over.\n| know we were careful to limit this guy’s exposure to the non-\nordinary (drugging him and carrying him through the upper floor\nwas a real hoot, by the way), but we really need to re-evaluate our\npolicies on external contractors. Honestly we'd be better off\nforming a special division trained in rappelling and orienteering than\nsubjecting more outsiders to the shit we deal with. They almost\nalways end up dead or loony.\n- Marcus",
  "error": null,
  "engine": "tesseract.js",
  "language": "eng",
  "translatedText": "OFICINA FEDERAL DE CONTROL OREAU ¢\nS 2\n\nSr. Wilder, = 20\n| tengo malas noticias. Te acuerdas de S Ei\":fr:’, ’8\nEse tipo, Robert Ricardo, que trajimos como \" 5‘“ 'K_[\"ill 3£: N\nun “consultor especial” para mapear el é,&% &Q}d’ inferior\ncuevas? Pues hoy encontró una cámara ‘osh = S\ncon ojos extraños que cubren cada centímetro de\nlas paredes, y un extraño pilar negro en el centro. un poco parece\nel del Cruce, pero más pequeño.\nTeníamos un miembro de la Oficina siguiéndolo, pero pase lo que pase\nAllí le hicieron un número a nuestro invitado. Los doctores están echando un vistazo pero\nEstá bastante claro que los días de exploración del Sr. Adventure han terminado.\n| Sabemos que tuvimos cuidado de limitar la exposición de este tipo a lo no\nordinario (drogándolo y cargándolo por el piso superior\nfue un verdadero puntazo, por cierto), pero realmente necesitamos reevaluar nuestra\npolíticas sobre contratistas externos. Sinceramente estaríamos mejor\nformando una división especial entrenada en rappel y orientación que\nsometiendo a más forasteros a la mierda con la que lidiamos. ellos casi\nSiempre terminas muerto o loco.\n- Marco",
  "translationEngine": "translatte",
  "translationDate": "2026-04-07T17:53:04.544Z"
}