{
  "imagePath": "images/research/pyramidic_geometry.png",
  "extractedText": "ON THE PYRAMID AND GEOMETRY\nI've been going through my library, researching pyramids and\ntriangles. If that shape does relate to the Board as Northmoor says,\nthen perhaps our predecessors in the occult can offer some insight\nthrough their geometric knowledge.\nIn esotericism, the triangle is closely associated with the Holy\nTrinity and other three-part concepts. Past, present, future. Mind,\nbody, spirit. Interestingly, the term “Board” also implies multiple\nparts.\nUpright triangles in Judeo-Christian imagery indicate ascent into\nthe rational/divine realm. Inverted, it signifies a descent into the\ncorporeal/human. Naturally, the ascent is masculine and the fall is\nfeminine. Adam and Eve. That's just a bit of old-world patriarchy.\nIt's 1964 now and we're well past that silliness.\nConsidering the above, what does the inverted triangle tell us\nabout the Board? They're clearly not corporeal or human. Perhaps\nthey wish to be? Or they once were? The likeliest answer is simply\nthat theological imagery cannot help us define alien entities.\nBut still, the pyramid seems significant. Shapes have power and\nclearly so does the Board.",
  "error": null,
  "engine": "tesseract.js",
  "language": "eng"
}