{
  "imagePath": "images/non-official_correspondence/interrogation_complaint.png",
  "extractedText": "Kirklund,\n\nSo you put me on desk duty just because | did the thing | was\nfucking hired to do? My JOB? Want to know what | call that?\nBULLSHIT.\n\nAsking us to interrogate these scum without using words like\n“Altered ltems” or “AWESs\" or “paracriminal” is the stupidest thing\nI've heard in my life and I've heard some fucking stupid things. They\nalready know the facts, hell, they know just as much as us, if not\nMORE. And they get to sit there laughing at us while we dance\naround our words, trying not to leak “classified terminology”. They\nalready know the fucking terminology!\n\nIf you think pulling me off the case will stop me, then think again.\nThat piece of shit blew up those tracks. He killed those people, all\nto make a train turn altered. We have him dead to rights and you\nneed to let me back in that interrogation cell so | can get him to flip\non his buddies. These people are terrorists and deserve to be\ntreated as such. This won't stop unless we stop them.\n\nYou can go ahead and put me on suspension, see if that slows me\ndown.\n\n- Agent Hewitt",
  "error": null,
  "engine": "tesseract.js",
  "language": "eng"
}