{
  "imagePath": "images/research/foundation_etchings.png",
  "extractedText": "ON THE FOUR ETCHINGS\nMy explorations of the Foundation have resulted in yet another\nmystery: a fascinating series of etchings on large stone tablets.\nThe tablets themselves are likely not native to the Foundation,\nseeing as they're slabs of sedimentary stone, quite different from\nthe cave's categorization-defying rock. Their placement and form\nare also too intentional to be naturally occurring. But who braved\nthis place to carry them in? And for what purpose? | discovered a\nfive-point macro-entanglement between the tablets, with the pillar\nat its center. These links seem to extend beyond our level of\nconsciousness, to some astral realm | can't detect. Is Northmoor's\nBoard somehow tied to all this?\nThe etchings on these tablets are similarly curious. They differ from\nthe cave paintings in style and technique, so are clearly not of the\nsame origin. Are they the visual narration of some event? Or do\nthey indicate intent, a wish, a plan®? They only seem to consist of a\ntree and the pillar, but the sizes of either are inconsistent. What\ndoes that signify?\nI'm missing key pieces of this puzzle and it's unlikely I'll ever find\nthem.",
  "error": null,
  "engine": "tesseract.js",
  "language": "eng",
  "translatedText": "SOBRE LOS CUATRO GRABADOS\nMis exploraciones de la Fundación han dado como resultado otro\nmisterio: una fascinante serie de grabados en grandes tablillas de piedra.\nEs probable que las tabletas en sí no sean nativas de la Fundación,\nya que son losas de piedra sedimentaria, muy diferentes a las\nla roca que desafía la categorización de la cueva. Su ubicación y forma.\nTambién son demasiado intencionales para ocurrir naturalmente. Pero ¿quién se atrevió\n¿Este lugar para llevarlos? ¿Y con qué propósito? | descubrió un\nmacroentrelazamiento de cinco puntos entre las tabletas, con el pilar\nen su centro. Estos vínculos parecen extenderse más allá de nuestro nivel de\nconciencia, a algún reino astral | No puedo detectar. es de Northmoor\n¿Junta de alguna manera ligada a todo esto?\nLos grabados de estas tablillas son igualmente curiosos. Se diferencian de\nlas pinturas rupestres en estilo y técnica, por lo que claramente no son del\nmismo origen. ¿Son la narración visual de algún evento? O hacer\n¿indican una intención, un deseo, un plan®? Sólo parecen consistir en un\nárbol y el pilar, pero los tamaños de ambos son inconsistentes. que\n¿Eso significa?\nMe faltan piezas claves de este rompecabezas y es poco probable que alguna vez las encuentre.\nellos.",
  "translationEngine": "translatte",
  "translationDate": "2026-04-07T17:55:30.452Z"
}